sf_etl_py2/Db2Db.py
sf_etl_py2/__init__.py
test/__init__.py
test/test.py
example_pkg_sf_etl_py2-0.0.1.dist-info/LICENSE
example_pkg_sf_etl_py2-0.0.1.dist-info/METADATA
example_pkg_sf_etl_py2-0.0.1.dist-info/WHEEL
example_pkg_sf_etl_py2-0.0.1.dist-info/top_level.txt
example_pkg_sf_etl_py2-0.0.1.dist-info/RECORD
