Metadata-Version: 2.1
Name: example-pkg-sf-etl-py2
Version: 0.0.1
Summary: test zzz
Home-page: UNKNOWN
Author: iszzZ
Author-email: xxx@foxmail.com
License: UNKNOWN
Platform: UNKNOWN
Classifier: Programming Language :: Python :: 2
Classifier: License :: OSI Approved :: MIT License
Classifier: Operating System :: OS Independent
Requires-Python: >=2.7
